heudiconv/__init__.py
heudiconv/_version.py
heudiconv/bids.py
heudiconv/convert.py
heudiconv/dicoms.py
heudiconv/due.py
heudiconv/info.py
heudiconv/main.py
heudiconv/parser.py
heudiconv/py.typed
heudiconv/queue.py
heudiconv/utils.py
heudiconv/cli/__init__.py
heudiconv/cli/monitor.py
heudiconv/cli/run.py
heudiconv/external/__init__.py
heudiconv/external/dlad.py
heudiconv/external/tests/__init__.py
heudiconv/external/tests/test_dlad.py
heudiconv/heuristics/__init__.py
heudiconv/heuristics/banda-bids.py
heudiconv/heuristics/bids_ME.py
heudiconv/heuristics/bids_PhoenixReport.py
heudiconv/heuristics/bids_with_ses.py
heudiconv/heuristics/cmrr_heuristic.py
heudiconv/heuristics/convertall.py
heudiconv/heuristics/convertall_custom.py
heudiconv/heuristics/example.py
heudiconv/heuristics/multires_7Tbold.py
heudiconv/heuristics/reproin.py
heudiconv/heuristics/studyforrest_phase2.py
heudiconv/heuristics/test_b0dwi_for_fmap.py
heudiconv/heuristics/test_reproin.py
heudiconv/heuristics/uc_bids.py
heudiconv/tests/__init__.py
heudiconv/tests/anonymize_script.py
heudiconv/tests/conftest.py
heudiconv/tests/test_archives.py
heudiconv/tests/test_bids.py
heudiconv/tests/test_convert.py
heudiconv/tests/test_dicoms.py
heudiconv/tests/test_heuristics.py
heudiconv/tests/test_main.py
heudiconv/tests/test_monitor.py
heudiconv/tests/test_queue.py
heudiconv/tests/test_regression.py
heudiconv/tests/test_tarballs.py
heudiconv/tests/test_utils.py
heudiconv/tests/utils.py
heudiconv/tests/data/MRI_102TD_PHA_S.MR.Chen_Matthews_1.3.1.2022.11.16.15.50.20.357.31204541.dcm
heudiconv/tests/data/axasc35.dcm
heudiconv/tests/data/phantom.dcm
heudiconv/tests/data/sample_nifti.nii.gz
heudiconv/tests/data/sample_nifti_params.txt
heudiconv/tests/data/01-anat-scout/0001.dcm
heudiconv/tests/data/01-fmap_acq-3mm/1.3.12.2.1107.5.2.43.66112.2016101409263663466202201.dcm
heudiconv/tests/data/Phoenix/01+AA/01+AA+00001.dcm
heudiconv/tests/data/Phoenix/99+PhoenixDocument/99+PhoenixDocument+00001.dcm
heudiconv_ancp-0.1.2.dist-info/licenses/LICENSE
heudiconv_ancp-0.1.2.dist-info/METADATA
heudiconv_ancp-0.1.2.dist-info/WHEEL
heudiconv_ancp-0.1.2.dist-info/entry_points.txt
heudiconv_ancp-0.1.2.dist-info/top_level.txt
heudiconv_ancp-0.1.2.dist-info/RECORD
